pyseltongue/__init__.py
pyseltongue/_version.py
pyseltongue/polynomials.py
pyseltongue/primes.py
pyseltongue/sharing.py
pyseltongue-1.0.2.dist-info/AUTHORS
pyseltongue-1.0.2.dist-info/LICENSE
pyseltongue-1.0.2.dist-info/METADATA
pyseltongue-1.0.2.dist-info/WHEEL
pyseltongue-1.0.2.dist-info/top_level.txt
pyseltongue-1.0.2.dist-info/RECORD
