Metadata-Version: 2.1
Name: pyseltongue
Version: 1.0.2
Summary: "Tools for sharing secrets (like Bitcoin private keys) using shamir's secret sharing scheme."
Home-page: https://github.com/ginsburgnm/pyseltongue
Author: nginsburg
Author-email: ginsburgnm@gmail.com
License: MIT
Classifier: Intended Audience :: Developers
Classifier: License :: OSI Approved :: MIT License
Classifier: Operating System :: OS Independent
Classifier: Programming Language :: Python :: 3.5
Classifier: Programming Language :: Python :: 3.6
Classifier: Programming Language :: Python :: 3.7
Classifier: Programming Language :: Python :: 3.8
Classifier: Topic :: Security :: Cryptography
License-File: LICENSE
License-File: AUTHORS
